Geometrify/__init__.py
Geometrify/geometry.py
Geometrify-1.0.4.dist-info/LICENSE
Geometrify-1.0.4.dist-info/METADATA
Geometrify-1.0.4.dist-info/WHEEL
Geometrify-1.0.4.dist-info/top_level.txt
Geometrify-1.0.4.dist-info/RECORD
