Metadata-Version: 2.1
Name: Geometrify
Version: 1.0.4
Summary: Geometrify is a Python package for easy creation, manipulation,
Home-page: https://github.com/1abhi6/Geometrify
Author: Abhishek Santosh Gupta
Author-email: abhi@getifyme.com
License: MIT
Keywords: 2D geometry,Coordinate geometry,Coordinate datatype
Classifier: Programming Language :: Python :: 3
Classifier: Intended Audience :: Developers
Classifier: License :: OSI Approved :: MIT License
Classifier: Operating System :: OS Independent
Requires-Python: >=3.6
License-File: LICENSE
